README.md
setup.cfg
setup.py
BioDendro/__init__.py
BioDendro/cluster.py
BioDendro/plot.py
BioDendro/preprocess.py
BioDendro.egg-info/PKG-INFO
BioDendro.egg-info/SOURCES.txt
BioDendro.egg-info/dependency_links.txt
BioDendro.egg-info/entry_points.txt
BioDendro.egg-info/requires.txt
BioDendro.egg-info/top_level.txt