Metadata-Version: 2.1
Name: BioDendro
Version: 0.0.3
Summary: a package to cluster metabolomics data and plot dendrograms
Home-page: https://github.com/ccdmb/BioDendro
Author: Catherine Rawlinson
Author-email: catherine.rawlinson@curtin.edu.au
License: Apache Software License
Keywords: metabolomics bioinformatics plotting
Platform: UNKNOWN
Classifier: Development Status :: 4 - Beta
Classifier: Intended Audience :: Developers
Classifier: License :: OSI Approved :: Apache Software License
Classifier: Programming Language :: Python :: 3
Classifier: Programming Language :: Python :: 3.7
Classifier: Programming Language :: Python :: 3.8
Classifier: Programming Language :: Python :: 3.9
Provides-Extra: dev
Provides-Extra: test
